Metadata-Version: 2.4
Name: derivx-quant
Version: 0.1.0
Summary: Precificador de derivativos por building blocks (MC/LSMC, PDE CN, Heston FFT, IR Black-76) com DSL declarativa.
Author: Walter C. Neto
License: MIT
Classifier: Programming Language :: Python :: 3
Classifier: License :: OSI Approved :: MIT License
Classifier: Operating System :: OS Independent
Classifier: Intended Audience :: Science/Research
Classifier: Topic :: Scientific/Engineering :: Mathematics
Classifier: Topic :: Office/Business :: Financial
Requires-Python: >=3.11
Requires-Dist: numpy>=1.24
Provides-Extra: viz
Requires-Dist: matplotlib>=3.8; extra == "viz"
Provides-Extra: dev
Requires-Dist: pytest>=7; extra == "dev"
Requires-Dist: pytest-cov; extra == "dev"
Requires-Dist: build; extra == "dev"
Requires-Dist: twine; extra == "dev"
Requires-Dist: ruff; extra == "dev"
Requires-Dist: black; extra == "dev"
